op_iaga_parser-0.3.0.dist-info/licenses/LICENSE
op_parser/__init__.py
op_parser/downloader.py
op_parser/iaga_downloader.py
op_parser/iaga_parser.py
op_parser/op_parser.py
op_parser/utils.py
op_iaga_parser-0.3.0.dist-info/METADATA
op_iaga_parser-0.3.0.dist-info/WHEEL
op_iaga_parser-0.3.0.dist-info/top_level.txt
op_iaga_parser-0.3.0.dist-info/RECORD
