Metadata-Version: 2.4
Name: op_iaga_parser
Version: 0.3.0
Summary: Library for downloading and parsing Op and IAGA-2002 scientific data formats
Home-page: https://github.com/31iwnl/op_parser
Author: 31iwnl
Author-email: xhispeco2018@gmail.com
Classifier: Programming Language :: Python :: 3
Classifier: License :: OSI Approved :: MIT License
Classifier: Operating System :: OS Independent
Requires-Python: >=3.7
License-File: LICENSE
Requires-Dist: requests
Dynamic: author
Dynamic: author-email
Dynamic: classifier
Dynamic: description
Dynamic: description-content-type
Dynamic: home-page
Dynamic: license-file
Dynamic: requires-dist
Dynamic: requires-python
Dynamic: summary
